xml_encoder/__init__.py
xml_encoder-1.0.0.dist-info/LICENSE
xml_encoder-1.0.0.dist-info/METADATA
xml_encoder-1.0.0.dist-info/WHEEL
xml_encoder-1.0.0.dist-info/top_level.txt
xml_encoder-1.0.0.dist-info/RECORD
